gaus_bin_probabilities/Binomialdistribution.py
gaus_bin_probabilities/Gaussiandistribution.py
gaus_bin_probabilities/Generaldistribution.py
gaus_bin_probabilities/__init__.py
gaus_bin_probabilities-0.1.dist-info/DESCRIPTION.rst
gaus_bin_probabilities-0.1.dist-info/METADATA
gaus_bin_probabilities-0.1.dist-info/RECORD
gaus_bin_probabilities-0.1.dist-info/WHEEL
gaus_bin_probabilities-0.1.dist-info/metadata.json
gaus_bin_probabilities-0.1.dist-info/top_level.txt
